.coveragerc
.coveralls.yml
.travis.yml
.travis.yml.org
MACOSX.txt
Makefile
README.rst
base.cfg
bootstrap.py
build_test.sh
buildout-plone-4.3.cfg
buildout-plone-5.0.cfg
buildout-plone-5.1.cfg
demo.cfg
demo5.cfg
dev-base.cfg
dev-plone-4.3.cfg
dev-plone-5.0.cfg
dev-plone-5.1.cfg
pdf.cfg
setup.cfg
setup.py
test_all.sh
test_webdav.sh
travis.cfg
docker/Dockerfile
docker/Makefile
docker/docker-xml-databases.sh
docker/start-all.sh
docker/base/Dockerfile
docker/base/Makefile
docker/base/exist-setup.cmd
docker/base+pp/Dockerfile
docker/base+pp/Makefile
docker/base+pp/exist-setup.cmd
docs/Makefile
docs/make.bat
docs/source/HISTORY.rst
docs/source/README.rst
docs/source/api.rst
docs/source/conf.py
docs/source/content-types.rst
docs/source/demo.rst
docs/source/index.rst
docs/source/known-issues.txt
docs/source/logging.rst
docs/source/pdf-generation.rst
docs/source/security.rst
docs/source/testing.rst
docs/source/transformation-pipeline.rst
docs/source/transformer-registry.rst
docs/source/validator-registry.rst
docs/source/images/xml-director-logo.jpg
scripts/api_demo.py
scripts/check_zipfiles.py
scripts/copy.py
scripts/hotfolder.py
scripts/test.docx
testing/ftp-server.py
xmldirector/__init__.py
xmldirector.plonecore.egg-info/PKG-INFO
xmldirector.plonecore.egg-info/SOURCES.txt
xmldirector.plonecore.egg-info/dependency_links.txt
xmldirector.plonecore.egg-info/entry_points.txt
xmldirector.plonecore.egg-info/namespace_packages.txt
xmldirector.plonecore.egg-info/not-zip-safe
xmldirector.plonecore.egg-info/requires.txt
xmldirector.plonecore.egg-info/top_level.txt
xmldirector/plonecore/__init__.py
xmldirector/plonecore/configure.zcml
xmldirector/plonecore/connector.py
xmldirector/plonecore/fswrapper.py
xmldirector/plonecore/header.txt
xmldirector/plonecore/i18n.py
xmldirector/plonecore/interfaces.py
xmldirector/plonecore/locking.py
xmldirector/plonecore/logger.py
xmldirector/plonecore/meta.zcml
xmldirector/plonecore/patches.py
xmldirector/plonecore/profiles-43.zcml
xmldirector/plonecore/profiles-51.zcml
xmldirector/plonecore/service.py
xmldirector/plonecore/transformation.py
xmldirector/plonecore/transformer_registry.py
xmldirector/plonecore/util.py
xmldirector/plonecore/validator_registry.py
xmldirector/plonecore/browser/__init__.py
xmldirector/plonecore/browser/ace_editor.pt
xmldirector/plonecore/browser/api.py
