Metadata-Version: 1.1
Name: xmldirector.plonecore
Version: 2.1.0
Summary: XML-Director 
Home-page: http://pypi.python.org/pypi/xmldirector.plonecore
Author: Andreas Jung
Author-email: info@zopyx.com
License: GPL
Keywords: xml-director exist-db basex owncloud alfresco existdb Plone XML Python WebDAV
Platform: UNKNOWN
Classifier: Programming Language :: Python
Classifier: Framework :: Plone
Classifier: Framework :: Plone :: 4.3
Classifier: Framework :: Plone :: 5.0
Classifier: Framework :: Plone :: 5.1
Classifier: Framework :: Zope2
Classifier: Topic :: Software Development :: Libraries :: Python Modules
